odoo/addons/sale_product_seasonality/README.rst
odoo/addons/sale_product_seasonality/__init__.py
odoo/addons/sale_product_seasonality/__manifest__.py
odoo/addons/sale_product_seasonality/utils.py
odoo/addons/sale_product_seasonality/i18n/fr.po
odoo/addons/sale_product_seasonality/i18n/sale_product_seasonality.pot
odoo/addons/sale_product_seasonality/models/__init__.py
odoo/addons/sale_product_seasonality/models/sale_order.py
odoo/addons/sale_product_seasonality/models/sale_order_line.py
odoo/addons/sale_product_seasonality/readme/CONFIGURE.rst
odoo/addons/sale_product_seasonality/readme/CONTRIBUTORS.rst
odoo/addons/sale_product_seasonality/readme/DESCRIPTION.rst
odoo/addons/sale_product_seasonality/readme/ROADMAP.rst
odoo/addons/sale_product_seasonality/static/description/icon.png
odoo/addons/sale_product_seasonality/static/description/index.html
odoo/addons/sale_product_seasonality/tests/__init__.py
odoo/addons/sale_product_seasonality/tests/common.py
odoo/addons/sale_product_seasonality/tests/test_sale_order.py
odoo/addons/sale_product_seasonality/views/menu.xml
odoo/addons/sale_product_seasonality/views/sale_order.xml
odoo14_addon_sale_product_seasonality-14.0.1.2.0.dist-info/METADATA
odoo14_addon_sale_product_seasonality-14.0.1.2.0.dist-info/WHEEL
odoo14_addon_sale_product_seasonality-14.0.1.2.0.dist-info/top_level.txt
odoo14_addon_sale_product_seasonality-14.0.1.2.0.dist-info/RECORD
